src/postgres-wrangler/__init__.py
src/postgres-wrangler/postgresql.py
postgres_wrangler-0.0.1.dist-info/METADATA
postgres_wrangler-0.0.1.dist-info/WHEEL
postgres_wrangler-0.0.1.dist-info/RECORD
